{"type":"Feature",
 "geometry":{"type":"Point","coordinates":[-121.694481734654,39.2886215770439]},
 "properties":{"prmname":"HGU5",
 "description":"Hidden node for calibration of GW-5",
 "type":"Junction",
 "origins":["INT CVPM5","EXT YUBA","EXT CVPM5"],
 "terminals":["GW-5"],
 "inflows":null}}
