{"type":"FeatureCollection","features":[{"type":"Feature",
 "geometry":{"type":"Point","coordinates":[-119.026208975917,35.1799662932064]},
 "properties":{"prmname":"U409",
 "description":"",
 "type":"Junction",
 "inflows":null,
 "sinks":null}},{"type":"Feature",
 "geometry":{"type":"Point","coordinates":[-118.972420626594,35.1066432757423]},
 "properties":{"prmname":"INT CVPM21",
 "description":"100% of DAU 258 and 26, interior",
 "type":"Urban Demand",
 "inflows":null,
 "sinks":null}},{"type":"Feature",
 "geometry":{"type":"Point","coordinates":[-118.972420626594,35.1066432757423]},
 "properties":{"prmname":"EXT CVPM21",
 "description":"100% of DAU 258 and 26, exterior",
 "type":"Urban Demand",
 "inflows":null,
 "sinks":null}},{"type":"Feature",
 "geometry":null,
 "properties":{"prmname":"U409_EXT CVPM21",
 "description":"",
 "type":"Diversion",
 "origin":"U409",
 "terminus":"EXT CVPM21",
 "amplitude":1,
 "costs":{"type":"Constant",
 "cost":0},
 "bounds":[{"type":"EQT","bound": {"$ref":"./EQT.csv"}}],
 "sinks":null}},{"type":"Feature",
 "geometry":null,
 "properties":{"prmname":"U409_EXT CVPM21",
 "description":"",
 "type":"Diversion",
 "origin":"U409",
 "terminus":"EXT CVPM21",
 "amplitude":1,
 "costs":{"type":"Constant",
 "cost":0},
 "bounds":[{"type":"EQT","bound": {"$ref":"./EQT.csv"}}],
 "sinks":null}},{"type":"Feature",
 "geometry":null,
 "properties":{"prmname":"U409_EXT CVPM21",
 "description":"",
 "type":"Diversion",
 "origin":"U409",
 "terminus":"EXT CVPM21",
 "amplitude":1,
 "costs":{"type":"Constant",
 "cost":0},
 "bounds":[{"type":"EQT","bound": {"$ref":"./EQT.csv"}}],
 "sinks":null}},{"type":"Feature",
 "geometry":null,
 "properties":{"prmname":"U409_INT CVPM21",
 "description":"",
 "type":"Diversion",
 "origin":"U409",
 "terminus":"INT CVPM21",
 "amplitude":1,
 "costs":{"type":"Constant",
 "cost":0},
 "bounds":[{"type":"EQT","bound": {"$ref":"./EQT.csv"}}],
 "sinks":null}},{"type":"Feature",
 "geometry":null,
 "properties":{"prmname":"U409_INT CVPM21",
 "description":"",
 "type":"Diversion",
 "origin":"U409",
 "terminus":"INT CVPM21",
 "amplitude":1,
 "costs":{"type":"Constant",
 "cost":0},
 "bounds":[{"type":"EQT","bound": {"$ref":"./EQT.csv"}}],
 "sinks":null}},{"type":"Feature",
 "geometry":null,
 "properties":{"prmname":"U409_INT CVPM21",
 "description":"",
 "type":"Diversion",
 "origin":"U409",
 "terminus":"INT CVPM21",
 "amplitude":1,
 "costs":{"type":"Constant",
 "cost":0},
 "bounds":[{"type":"EQT","bound": {"$ref":"./EQT.csv"}}],
 "sinks":null}}]}
