{"type":"Feature",
 "geometry":{"type":"Point","coordinates":[-121.245406215509,38.9578925550485]},
 "properties":{"prmname":"HGP5",
 "description":"Hidden node for calibration of GW-5",
 "type":"Junction",
 "origins":["GW-5"],
 "terminals":["INT CVPM5","EXT CVPM5","C26","T61YUBA"],
 "inflows":null}}
