{"type":"Feature",
 "geometry":{"type":"Point","coordinates":[-121.245406215509,38.9578925550485]},
 "properties":{"prmname":"HGP5",
 "description":"Hidden node for calibration of GW-5",
 "type":"Junction",
 "origins":["GW-5"],
 "terminals":["INT CVPM5","T61YUBA","EXT CVPM5","CVPM5","C26"],
 "inflows":null}}
