{"type":"Feature",
 "geometry":{"type":"Point","coordinates":[-117.862728451475,34.0343816478517]},
 "properties":{"prmname":"T10CMWD",
 "description":"Central MWD OUT",
 "type":"Water Treatment",
 "origins":["Ind: CMWD","IRes CMWD"],
 "terminals":["HWWT10","T5CMWD","Sink G37"],
 "inflows":null}}
