{"type":"Feature",
 "geometry":{"type":"Point","coordinates":[-119.272875113907,36.0211436935293]},
 "properties":{"prmname":"HAR18",
 "description":"Artificial recharge node",
 "type":"Junction",
 "origins":["C56","C58","C688"],
 "terminals":["GW-18"],
 "inflows":null}}
