{"type":"Feature",
 "geometry":{"type":"Point","coordinates":[-115.459403055922,33.012149917051]},
 "properties":{"prmname":"T57ECEN",
 "description":"Urban water treatment node for El Centro",
 "type":"Water Treatment",
 "origins":["T58ECEN","C152"],
 "terminals":["INT El Cen","EXT El Cen"],
 "inflows":null}}
