{"type":"Feature",
 "geometry":{"type":"Point","coordinates":[-122.078272760759,39.3878822921032]},
 "properties":{"prmname":"HGP4",
 "description":"Hidden node for calibration of GW-4",
 "type":"Junction",
 "origins":["GW-4"],
 "terminals":["C14","CVPM4","EXT CVPM4","INT CVPM4"],
 "inflows":null}}
