{"type":"Feature",
 "geometry":{"type":"Point","coordinates":[-117.862728451475,34.0343816478517]},
 "properties":{"prmname":"T5CMWD",
 "description":"Central MWD IN",
 "type":"Water Treatment",
 "origins":["HWWT10","GW-MWD","C161","DesalR5","T10CMWD"],
 "terminals":["Ind: CMWD","IRes CMWD","HXCMWD"],
 "inflows":null}}
