{"type":"Feature",
 "geometry":{"type":"Point","coordinates":[-117.862728451475,34.0343816478517]},
 "properties":{"prmname":"T5CMWD",
 "description":"Central MWD IN",
 "type":"Water Treatment",
 "origins":["T10CMWD","HWWT10","DesalR5","C161","GW-MWD"],
 "terminals":["Ind: CMWD","HXCMWD","IRes CMWD"],
 "inflows":null}}
