{"type":"Feature",
 "geometry":{"type":"Point","coordinates":[-119.134545111916,35.2909192932068]},
 "properties":{"prmname":"T29BAKE",
 "description":"Bakersfield OUT",
 "type":"Water Treatment",
 "origins":["INT BAKER"],
 "terminals":["HGU21","C73","T28BAKE"],
 "inflows":null}}
