{"type":"Feature",
 "geometry":{"type":"Point","coordinates":[-121.139396298091,38.0576188365164]},
 "properties":{"prmname":"T27STOC",
 "description":"Stockton OUT",
 "type":"Water Treatment",
 "origins":["INT STOCK"],
 "terminals":["T26STOC","C42","HGU8"],
 "inflows":null}}
